yahoo-earnings-calendar/__init__.py
yahoo-earnings-calendar/sample.py
yahoo_earnings_calendar/__init__.py
yahoo_earnings_calendar/sample.py
yahoo_earnings_calendar/scraper.py
yahoo_earnings_calendar-0.6.0.dist-info/LICENSE
yahoo_earnings_calendar-0.6.0.dist-info/METADATA
yahoo_earnings_calendar-0.6.0.dist-info/WHEEL
yahoo_earnings_calendar-0.6.0.dist-info/top_level.txt
yahoo_earnings_calendar-0.6.0.dist-info/RECORD
