Metadata-Version: 2.1
Name: yahoo-earnings-calendar
Version: 0.6.0
Summary: Scrapes data from Yahoo! Finance earnings calendar
Home-page: https://github.com/wenboyu2/yahoo-earnings-calendar
Author: Wenbo Yu
Author-email: wenboyu2@gmail.com
License: UNKNOWN
Keywords: stock,earnings,yahoo,scrape,finance
Platform: UNKNOWN
Classifier: Development Status :: 4 - Beta
Classifier: Intended Audience :: Developers
Classifier: Intended Audience :: Financial and Insurance Industry
Classifier: Natural Language :: English
Classifier: Programming Language :: Python
Classifier: Programming Language :: Python :: 2
Classifier: Programming Language :: Python :: 2.7
Classifier: Programming Language :: Python :: 3
Classifier: Programming Language :: Python :: 3.4
Classifier: Programming Language :: Python :: 3.5
Classifier: Programming Language :: Python :: 3.6
Classifier: Programming Language :: Python :: 3.7
